<Proxy>
  <ListenPort>8888</ListenPort>
  <NetConnectName>
  </NetConnectName>
  <ValidateProxy2Url>http://www.baidu.com/</ValidateProxy2Url>
  <ValidateProxy2RetrunString>&lt;title&gt;百度一下，你就知道</ValidateProxy2RetrunString>
  <ValidateTimeOut>5</ValidateTimeOut>
  <IsOrderOrRandomGetProxys>1</IsOrderOrRandomGetProxys>
  <IsADSLReconnect>0</IsADSLReconnect>
  <IsADSLReconnect_IntervalOrContainString>0</IsADSLReconnect_IntervalOrContainString>
  <ReconnectIntervalMinute>90</ReconnectIntervalMinute>
  <ReconnectIfContainString>
  </ReconnectIfContainString>
  <SampleProxySite>
  </SampleProxySite>
  <Level2Proxys>
    <ProxyItem Type="0" IP="220.181.32.106" Port="80" UserName="" PassWord="" Domain="" IsValidate="0" />
    <ProxyItem Type="0" IP="182.254.153.54" Port="80" UserName="" PassWord="" Domain="" IsValidate="0" />
    <ProxyItem Type="0" IP="112.25.41.136" Port="80" UserName="" PassWord="" Domain="" IsValidate="0" />
    <ProxyItem Type="0" IP="101.226.249.237" Port="80" UserName="" PassWord="" Domain="" IsValidate="0" />
    <ProxyItem Type="0" IP="115.159.5.247" Port="80" UserName="" PassWord="" Domain="" IsValidate="0" />
    <ProxyItem Type="0" IP="180.97.185.35" Port="10001" UserName="" PassWord="" Domain="" IsValidate="0" />
    <ProxyItem Type="0" IP="117.177.243.40" Port="8080" UserName="" PassWord="" Domain="" IsValidate="0" />
    <ProxyItem Type="0" IP="101.71.27.120" Port="80" UserName="" PassWord="" Domain="" IsValidate="0" />
    <ProxyItem Type="0" IP="122.96.59.105" Port="843" UserName="" PassWord="" Domain="" IsValidate="0" />
    <ProxyItem Type="0" IP="1.60.157.2" Port="9000" UserName="" PassWord="" Domain="" IsValidate="0" />
    <ProxyItem Type="0" IP="119.176.82.229" Port="9000" UserName="" PassWord="" Domain="" IsValidate="0" />
    <ProxyItem Type="0" IP="183.22.134.12" Port="8090" UserName="" PassWord="" Domain="" IsValidate="0" />
    <ProxyItem Type="0" IP="171.37.146.15" Port="8090" UserName="" PassWord="" Domain="" IsValidate="0" />
    <ProxyItem Type="0" IP="116.228.143.200" Port="80" UserName="" PassWord="" Domain="" IsValidate="0" />
    <ProxyItem Type="0" IP="111.183.152.179" Port="9000" UserName="" PassWord="" Domain="" IsValidate="0" />
    <ProxyItem Type="0" IP="115.223.253.128" Port="9000" UserName="" PassWord="" Domain="" IsValidate="0" />
    <ProxyItem Type="0" IP="220.177.174.181" Port="9000" UserName="" PassWord="" Domain="" IsValidate="0" />
    <ProxyItem Type="0" IP="119.177.84.242" Port="9000" UserName="" PassWord="" Domain="" IsValidate="0" />
    <ProxyItem Type="0" IP="218.91.20.116" Port="8090" UserName="" PassWord="" Domain="" IsValidate="0" />
    <ProxyItem Type="0" IP="118.249.117.206" Port="9000" UserName="" PassWord="" Domain="" IsValidate="0" />
    <ProxyItem Type="0" IP="218.64.40.168" Port="8090" UserName="" PassWord="" Domain="" IsValidate="0" />
    <ProxyItem Type="0" IP="112.64.30.230" Port="8090" UserName="" PassWord="" Domain="" IsValidate="0" />
    <ProxyItem Type="0" IP="1.60.156.141" Port="9000" UserName="" PassWord="" Domain="" IsValidate="0" />
    <ProxyItem Type="0" IP="183.130.87.145" Port="9000" UserName="" PassWord="" Domain="" IsValidate="0" />
    <ProxyItem Type="0" IP="27.191.71.130" Port="8090" UserName="" PassWord="" Domain="" IsValidate="0" />
    <ProxyItem Type="0" IP="118.239.148.238" Port="9000" UserName="" PassWord="" Domain="" IsValidate="0" />
    <ProxyItem Type="0" IP="112.64.29.249" Port="8090" UserName="" PassWord="" Domain="" IsValidate="0" />
    <ProxyItem Type="0" IP="115.214.10.189" Port="8090" UserName="" PassWord="" Domain="" IsValidate="0" />
    <ProxyItem Type="0" IP="122.226.156.220" Port="3128" UserName="" PassWord="" Domain="" IsValidate="0" />
    <ProxyItem Type="0" IP="223.150.18.206" Port="9000" UserName="" PassWord="" Domain="" IsValidate="0" />
    <ProxyItem Type="0" IP="115.150.14.114" Port="9000" UserName="" PassWord="" Domain="" IsValidate="0" />
    <ProxyItem Type="0" IP="121.42.152.19" Port="80" UserName="" PassWord="" Domain="" IsValidate="0" />
    <ProxyItem Type="0" IP="115.218.197.202" Port="9000" UserName="" PassWord="" Domain="" IsValidate="0" />
    <ProxyItem Type="0" IP="113.107.57.76" Port="8101" UserName="" PassWord="" Domain="" IsValidate="0" />
    <ProxyItem Type="0" IP="115.153.172.79" Port="9000" UserName="" PassWord="" Domain="" IsValidate="0" />
    <ProxyItem Type="0" IP="119.7.95.70" Port="9000" UserName="" PassWord="" Domain="" IsValidate="0" />
    <ProxyItem Type="0" IP="49.82.198.192" Port="9000" UserName="" PassWord="" Domain="" IsValidate="0" />
    <ProxyItem Type="0" IP="119.7.90.158" Port="9000" UserName="" PassWord="" Domain="" IsValidate="0" />
    <ProxyItem Type="0" IP="60.219.21.43" Port="9000" UserName="" PassWord="" Domain="" IsValidate="0" />
    <ProxyItem Type="0" IP="112.112.131.45" Port="8090" UserName="" PassWord="" Domain="" IsValidate="0" />
    <ProxyItem Type="0" IP="49.84.104.139" Port="9000" UserName="" PassWord="" Domain="" IsValidate="0" />
    <ProxyItem Type="0" IP="115.218.125.84" Port="9000" UserName="" PassWord="" Domain="" IsValidate="0" />
    <ProxyItem Type="0" IP="124.152.208.213" Port="8090" UserName="" PassWord="" Domain="" IsValidate="0" />
    <ProxyItem Type="0" IP="112.64.30.220" Port="8090" UserName="" PassWord="" Domain="" IsValidate="0" />
    <ProxyItem Type="0" IP="112.195.80.178" Port="9000" UserName="" PassWord="" Domain="" IsValidate="0" />
    <ProxyItem Type="0" IP="115.223.224.220" Port="9000" UserName="" PassWord="" Domain="" IsValidate="0" />
    <ProxyItem Type="0" IP="118.249.118.128" Port="9000" UserName="" PassWord="" Domain="" IsValidate="0" />
    <ProxyItem Type="0" IP="115.151.241.112" Port="9000" UserName="" PassWord="" Domain="" IsValidate="0" />
    <ProxyItem Type="0" IP="60.191.103.162" Port="3128" UserName="" PassWord="" Domain="" IsValidate="0" />
    <ProxyItem Type="0" IP="222.95.250.73" Port="8090" UserName="" PassWord="" Domain="" IsValidate="0" />
    <ProxyItem Type="0" IP="115.153.162.229" Port="9000" UserName="" PassWord="" Domain="" IsValidate="0" />
    <ProxyItem Type="0" IP="113.3.87.185" Port="9000" UserName="" PassWord="" Domain="" IsValidate="0" />
    <ProxyItem Type="0" IP="115.218.122.63" Port="9000" UserName="" PassWord="" Domain="" IsValidate="0" />
    <ProxyItem Type="0" IP="61.162.184.14" Port="8080" UserName="" PassWord="" Domain="" IsValidate="0" />
    <ProxyItem Type="0" IP="182.101.221.170" Port="9000" UserName="" PassWord="" Domain="" IsValidate="0" />
    <ProxyItem Type="0" IP="118.249.116.249" Port="9000" UserName="" PassWord="" Domain="" IsValidate="0" />
    <ProxyItem Type="0" IP="115.223.224.216" Port="9000" UserName="" PassWord="" Domain="" IsValidate="0" />
    <ProxyItem Type="0" IP="59.55.58.46" Port="9000" UserName="" PassWord="" Domain="" IsValidate="0" />
    <ProxyItem Type="0" IP="115.223.245.210" Port="9000" UserName="" PassWord="" Domain="" IsValidate="0" />
    <ProxyItem Type="0" IP="110.248.191.231" Port="8080" UserName="" PassWord="" Domain="" IsValidate="0" />
    <ProxyItem Type="0" IP="49.84.107.248" Port="9000" UserName="" PassWord="" Domain="" IsValidate="0" />
    <ProxyItem Type="0" IP="106.114.210.97" Port="8090" UserName="" PassWord="" Domain="" IsValidate="0" />
    <ProxyItem Type="0" IP="59.62.16.24" Port="9000" UserName="" PassWord="" Domain="" IsValidate="0" />
    <ProxyItem Type="0" IP="182.99.178.49" Port="9000" UserName="" PassWord="" Domain="" IsValidate="0" />
    <ProxyItem Type="0" IP="112.64.185.73" Port="80" UserName="" PassWord="" Domain="" IsValidate="0" />
    <ProxyItem Type="0" IP="27.214.72.161" Port="9000" UserName="" PassWord="" Domain="" IsValidate="0" />
    <ProxyItem Type="0" IP="115.218.221.233" Port="9000" UserName="" PassWord="" Domain="" IsValidate="0" />
    <ProxyItem Type="0" IP="112.95.205.152" Port="8888" UserName="" PassWord="" Domain="" IsValidate="0" />
    <ProxyItem Type="0" IP="182.101.220.43" Port="9000" UserName="" PassWord="" Domain="" IsValidate="0" />
    <ProxyItem Type="0" IP="218.95.50.254" Port="9000" UserName="" PassWord="" Domain="" IsValidate="0" />
    <ProxyItem Type="0" IP="119.188.115.28" Port="8080" UserName="" PassWord="" Domain="" IsValidate="0" />
    <ProxyItem Type="0" IP="119.7.94.41" Port="9000" UserName="" PassWord="" Domain="" IsValidate="0" />
    <ProxyItem Type="0" IP="112.25.171.125" Port="8000" UserName="" PassWord="" Domain="" IsValidate="0" />
    <ProxyItem Type="0" IP="182.101.223.187" Port="9000" UserName="" PassWord="" Domain="" IsValidate="0" />
    <ProxyItem Type="0" IP="115.223.216.97" Port="9000" UserName="" PassWord="" Domain="" IsValidate="0" />
    <ProxyItem Type="0" IP="183.62.206.210" Port="3128" UserName="" PassWord="" Domain="" IsValidate="0" />
    <ProxyItem Type="0" IP="113.218.86.175" Port="9000" UserName="" PassWord="" Domain="" IsValidate="0" />
    <ProxyItem Type="0" IP="223.150.140.156" Port="9000" UserName="" PassWord="" Domain="" IsValidate="0" />
    <ProxyItem Type="0" IP="115.218.217.193" Port="9000" UserName="" PassWord="" Domain="" IsValidate="0" />
    <ProxyItem Type="0" IP="112.194.82.168" Port="9000" UserName="" PassWord="" Domain="" IsValidate="0" />
    <ProxyItem Type="0" IP="124.161.153.25" Port="9000" UserName="" PassWord="" Domain="" IsValidate="0" />
    <ProxyItem Type="0" IP="218.64.148.175" Port="9000" UserName="" PassWord="" Domain="" IsValidate="0" />
    <ProxyItem Type="0" IP="1.63.196.103" Port="9000" UserName="" PassWord="" Domain="" IsValidate="0" />
    <ProxyItem Type="0" IP="115.223.217.207" Port="9000" UserName="" PassWord="" Domain="" IsValidate="0" />
    <ProxyItem Type="0" IP="115.62.32.244" Port="9000" UserName="" PassWord="" Domain="" IsValidate="0" />
    <ProxyItem Type="0" IP="118.255.23.53" Port="9000" UserName="" PassWord="" Domain="" IsValidate="0" />
    <ProxyItem Type="0" IP="218.57.85.40" Port="9999" UserName="" PassWord="" Domain="" IsValidate="0" />
    <ProxyItem Type="0" IP="218.30.35.86" Port="8080" UserName="" PassWord="" Domain="" IsValidate="0" />
    <ProxyItem Type="0" IP="222.246.232.55" Port="80" UserName="" PassWord="" Domain="" IsValidate="0" />
    <ProxyItem Type="0" IP="123.130.14.202" Port="8090" UserName="" PassWord="" Domain="" IsValidate="0" />
    <ProxyItem Type="0" IP="125.110.109.155" Port="9000" UserName="" PassWord="" Domain="" IsValidate="0" />
    <ProxyItem Type="0" IP="113.218.23.6" Port="9000" UserName="" PassWord="" Domain="" IsValidate="0" />
    <ProxyItem Type="0" IP="115.150.96.103" Port="9000" UserName="" PassWord="" Domain="" IsValidate="0" />
    <ProxyItem Type="0" IP="112.194.85.30" Port="9000" UserName="" PassWord="" Domain="" IsValidate="0" />
    <ProxyItem Type="0" IP="115.148.26.42" Port="9000" UserName="" PassWord="" Domain="" IsValidate="0" />
    <ProxyItem Type="0" IP="119.7.93.82" Port="9000" UserName="" PassWord="" Domain="" IsValidate="0" />
    <ProxyItem Type="0" IP="117.136.234.4" Port="80" UserName="" PassWord="" Domain="" IsValidate="0" />
    <ProxyItem Type="0" IP="115.153.161.17" Port="9000" UserName="" PassWord="" Domain="" IsValidate="0" />
    <ProxyItem Type="0" IP="115.151.244.41" Port="9000" UserName="" PassWord="" Domain="" IsValidate="0" />
    <ProxyItem Type="0" IP="115.223.216.74" Port="9000" UserName="" PassWord="" Domain="" IsValidate="0" />
    <ProxyItem Type="0" IP="223.151.155.192" Port="9000" UserName="" PassWord="" Domain="" IsValidate="0" />
    <ProxyItem Type="0" IP="125.105.229.75" Port="8090" UserName="" PassWord="" Domain="" IsValidate="0" />
    <ProxyItem Type="0" IP="115.151.207.182" Port="9000" UserName="" PassWord="" Domain="" IsValidate="0" />
    <ProxyItem Type="0" IP="115.218.218.5" Port="9000" UserName="" PassWord="" Domain="" IsValidate="0" />
    <ProxyItem Type="0" IP="112.195.81.188" Port="9000" UserName="" PassWord="" Domain="" IsValidate="0" />
    <ProxyItem Type="0" IP="27.12.195.74" Port="8090" UserName="" PassWord="" Domain="" IsValidate="0" />
    <ProxyItem Type="0" IP="218.64.148.37" Port="9000" UserName="" PassWord="" Domain="" IsValidate="0" />
    <ProxyItem Type="0" IP="222.85.127.130" Port="9999" UserName="" PassWord="" Domain="" IsValidate="0" />
    <ProxyItem Type="0" IP="115.218.126.178" Port="9000" UserName="" PassWord="" Domain="" IsValidate="0" />
    <ProxyItem Type="0" IP="223.151.249.148" Port="9000" UserName="" PassWord="" Domain="" IsValidate="0" />
    <ProxyItem Type="0" IP="115.223.248.53" Port="9000" UserName="" PassWord="" Domain="" IsValidate="0" />
    <ProxyItem Type="0" IP="120.24.248.225" Port="8080" UserName="" PassWord="" Domain="" IsValidate="0" />
    <ProxyItem Type="0" IP="119.7.92.27" Port="9000" UserName="" PassWord="" Domain="" IsValidate="0" />
    <ProxyItem Type="0" IP="59.55.59.87" Port="9000" UserName="" PassWord="" Domain="" IsValidate="0" />
    <ProxyItem Type="0" IP="182.201.249.4" Port="8090" UserName="" PassWord="" Domain="" IsValidate="0" />
    <ProxyItem Type="0" IP="183.247.166.176" Port="80" UserName="" PassWord="" Domain="" IsValidate="0" />
    <ProxyItem Type="0" IP="115.210.57.119" Port="8090" UserName="" PassWord="" Domain="" IsValidate="0" />
    <ProxyItem Type="0" IP="119.7.91.197" Port="9000" UserName="" PassWord="" Domain="" IsValidate="0" />
    <ProxyItem Type="0" IP="119.178.220.2" Port="9000" UserName="" PassWord="" Domain="" IsValidate="0" />
    <ProxyItem Type="0" IP="113.77.179.227" Port="8090" UserName="" PassWord="" Domain="" IsValidate="0" />
    <ProxyItem Type="0" IP="218.65.65.103" Port="9000" UserName="" PassWord="" Domain="" IsValidate="0" />
    <ProxyItem Type="0" IP="218.95.51.208" Port="9000" UserName="" PassWord="" Domain="" IsValidate="0" />
    <ProxyItem Type="0" IP="220.176.66.242" Port="9000" UserName="" PassWord="" Domain="" IsValidate="0" />
    <ProxyItem Type="0" IP="119.7.90.13" Port="9000" UserName="" PassWord="" Domain="" IsValidate="0" />
    <ProxyItem Type="0" IP="110.73.50.114" Port="8123" UserName="" PassWord="" Domain="" IsValidate="0" />
    <ProxyItem Type="0" IP="219.137.134.119" Port="8090" UserName="" PassWord="" Domain="" IsValidate="0" />
    <ProxyItem Type="0" IP="59.62.26.112" Port="9000" UserName="" PassWord="" Domain="" IsValidate="0" />
    <ProxyItem Type="0" IP="115.218.220.126" Port="9000" UserName="" PassWord="" Domain="" IsValidate="0" />
    <ProxyItem Type="0" IP="101.207.30.8" Port="8090" UserName="" PassWord="" Domain="" IsValidate="0" />
    <ProxyItem Type="0" IP="222.220.144.35" Port="3128" UserName="" PassWord="" Domain="" IsValidate="0" />
    <ProxyItem Type="0" IP="120.198.231.24" Port="80" UserName="" PassWord="" Domain="" IsValidate="0" />
    <ProxyItem Type="0" IP="220.176.93.233" Port="9000" UserName="" PassWord="" Domain="" IsValidate="0" />
    <ProxyItem Type="0" IP="27.206.75.132" Port="9000" UserName="" PassWord="" Domain="" IsValidate="0" />
    <ProxyItem Type="0" IP="223.151.135.46" Port="9000" UserName="" PassWord="" Domain="" IsValidate="0" />
    <ProxyItem Type="0" IP="112.195.86.156" Port="9000" UserName="" PassWord="" Domain="" IsValidate="0" />
    <ProxyItem Type="0" IP="115.151.251.138" Port="9000" UserName="" PassWord="" Domain="" IsValidate="0" />
    <ProxyItem Type="0" IP="183.223.24.122" Port="8000" UserName="" PassWord="" Domain="" IsValidate="0" />
    <ProxyItem Type="0" IP="117.136.234.9" Port="82" UserName="" PassWord="" Domain="" IsValidate="0" />
    <ProxyItem Type="0" IP="115.153.162.91" Port="9000" UserName="" PassWord="" Domain="" IsValidate="0" />
    <ProxyItem Type="0" IP="112.95.38.205" Port="8090" UserName="" PassWord="" Domain="" IsValidate="0" />
    <ProxyItem Type="0" IP="119.7.95.126" Port="9000" UserName="" PassWord="" Domain="" IsValidate="0" />
    <ProxyItem Type="0" IP="116.209.100.172" Port="9000" UserName="" PassWord="" Domain="" IsValidate="0" />
    <ProxyItem Type="0" IP="119.7.93.69" Port="9000" UserName="" PassWord="" Domain="" IsValidate="0" />
    <ProxyItem Type="0" IP="59.62.36.194" Port="9000" UserName="" PassWord="" Domain="" IsValidate="0" />
    <ProxyItem Type="0" IP="182.87.184.41" Port="9000" UserName="" PassWord="" Domain="" IsValidate="0" />
    <ProxyItem Type="0" IP="117.87.175.37" Port="9000" UserName="" PassWord="" Domain="" IsValidate="0" />
    <ProxyItem Type="0" IP="114.234.82.183" Port="9000" UserName="" PassWord="" Domain="" IsValidate="0" />
    <ProxyItem Type="0" IP="59.55.58.106" Port="9000" UserName="" PassWord="" Domain="" IsValidate="0" />
    <ProxyItem Type="0" IP="124.161.154.28" Port="9000" UserName="" PassWord="" Domain="" IsValidate="0" />
    <ProxyItem Type="0" IP="183.130.123.98" Port="9000" UserName="" PassWord="" Domain="" IsValidate="0" />
    <ProxyItem Type="0" IP="115.218.120.49" Port="9000" UserName="" PassWord="" Domain="" IsValidate="0" />
    <ProxyItem Type="0" IP="106.5.197.202" Port="9000" UserName="" PassWord="" Domain="" IsValidate="0" />
    <ProxyItem Type="0" IP="117.136.234.10" Port="82" UserName="" PassWord="" Domain="" IsValidate="0" />
    <ProxyItem Type="0" IP="119.187.72.81" Port="9000" UserName="" PassWord="" Domain="" IsValidate="0" />
    <ProxyItem Type="0" IP="116.27.49.223" Port="8090" UserName="" PassWord="" Domain="" IsValidate="0" />
    <ProxyItem Type="0" IP="220.176.93.78" Port="9000" UserName="" PassWord="" Domain="" IsValidate="0" />
    <ProxyItem Type="0" IP="220.176.146.217" Port="8090" UserName="" PassWord="" Domain="" IsValidate="0" />
    <ProxyItem Type="0" IP="183.22.128.8" Port="8090" UserName="" PassWord="" Domain="" IsValidate="0" />
    <ProxyItem Type="0" IP="59.55.58.21" Port="9000" UserName="" PassWord="" Domain="" IsValidate="0" />
    <ProxyItem Type="0" IP="115.151.208.115" Port="9000" UserName="" PassWord="" Domain="" IsValidate="0" />
    <ProxyItem Type="0" IP="223.95.84.179" Port="3128" UserName="" PassWord="" Domain="" IsValidate="0" />
    <ProxyItem Type="0" IP="60.191.170.122" Port="3128" UserName="" PassWord="" Domain="" IsValidate="0" />
    <ProxyItem Type="0" IP="61.164.0.212" Port="8080" UserName="" PassWord="" Domain="" IsValidate="0" />
    <ProxyItem Type="0" IP="182.87.187.146" Port="9000" UserName="" PassWord="" Domain="" IsValidate="0" />
    <ProxyItem Type="0" IP="60.29.248.142" Port="8080" UserName="" PassWord="" Domain="" IsValidate="0" />
    <ProxyItem Type="0" IP="119.7.89.195" Port="9000" UserName="" PassWord="" Domain="" IsValidate="0" />
    <ProxyItem Type="0" IP="59.55.58.70" Port="9000" UserName="" PassWord="" Domain="" IsValidate="0" />
    <ProxyItem Type="0" IP="113.5.227.24" Port="9000" UserName="" PassWord="" Domain="" IsValidate="0" />
    <ProxyItem Type="0" IP="182.101.220.189" Port="9000" UserName="" PassWord="" Domain="" IsValidate="0" />
    <ProxyItem Type="0" IP="115.223.212.241" Port="9000" UserName="" PassWord="" Domain="" IsValidate="0" />
    <ProxyItem Type="0" IP="182.40.59.38" Port="8090" UserName="" PassWord="" Domain="" IsValidate="0" />
    <ProxyItem Type="0" IP="113.3.87.52" Port="9000" UserName="" PassWord="" Domain="" IsValidate="0" />
    <ProxyItem Type="0" IP="113.224.73.198" Port="9000" UserName="" PassWord="" Domain="" IsValidate="0" />
    <ProxyItem Type="0" IP="115.150.96.50" Port="9000" UserName="" PassWord="" Domain="" IsValidate="0" />
    <ProxyItem Type="0" IP="119.7.93.76" Port="9000" UserName="" PassWord="" Domain="" IsValidate="0" />
    <ProxyItem Type="0" IP="218.64.46.251" Port="8090" UserName="" PassWord="" Domain="" IsValidate="0" />
    <ProxyItem Type="0" IP="115.153.162.176" Port="9000" UserName="" PassWord="" Domain="" IsValidate="0" />
    <ProxyItem Type="0" IP="115.150.97.62" Port="9000" UserName="" PassWord="" Domain="" IsValidate="0" />
    <ProxyItem Type="0" IP="119.7.95.182" Port="9000" UserName="" PassWord="" Domain="" IsValidate="0" />
    <ProxyItem Type="0" IP="115.223.214.92" Port="9000" UserName="" PassWord="" Domain="" IsValidate="0" />
    <ProxyItem Type="0" IP="119.137.77.188" Port="9999" UserName="" PassWord="" Domain="" IsValidate="0" />
    <ProxyItem Type="0" IP="180.109.137.213" Port="8090" UserName="" PassWord="" Domain="" IsValidate="0" />
    <ProxyItem Type="0" IP="180.104.92.15" Port="9000" UserName="" PassWord="" Domain="" IsValidate="0" />
    <ProxyItem Type="0" IP="119.187.72.206" Port="9000" UserName="" PassWord="" Domain="" IsValidate="0" />
    <ProxyItem Type="0" IP="220.176.159.71" Port="9000" UserName="" PassWord="" Domain="" IsValidate="0" />
    <ProxyItem Type="0" IP="115.150.111.29" Port="9000" UserName="" PassWord="" Domain="" IsValidate="0" />
    <ProxyItem Type="0" IP="115.223.213.143" Port="9000" UserName="" PassWord="" Domain="" IsValidate="0" />
    <ProxyItem Type="0" IP="218.3.76.28" Port="3128" UserName="" PassWord="" Domain="" IsValidate="0" />
    <ProxyItem Type="0" IP="112.95.86.86" Port="8090" UserName="" PassWord="" Domain="" IsValidate="0" />
    <ProxyItem Type="0" IP="115.151.215.186" Port="9000" UserName="" PassWord="" Domain="" IsValidate="0" />
    <ProxyItem Type="0" IP="220.176.149.202" Port="8090" UserName="" PassWord="" Domain="" IsValidate="0" />
    <ProxyItem Type="0" IP="112.243.122.29" Port="9000" UserName="" PassWord="" Domain="" IsValidate="0" />
    <ProxyItem Type="0" IP="113.218.14.210" Port="9000" UserName="" PassWord="" Domain="" IsValidate="0" />
    <ProxyItem Type="0" IP="115.153.167.13" Port="9000" UserName="" PassWord="" Domain="" IsValidate="0" />
    <ProxyItem Type="0" IP="115.218.121.234" Port="9000" UserName="" PassWord="" Domain="" IsValidate="0" />
    <ProxyItem Type="0" IP="183.130.101.15" Port="9000" UserName="" PassWord="" Domain="" IsValidate="0" />
    <ProxyItem Type="0" IP="115.218.126.90" Port="9000" UserName="" PassWord="" Domain="" IsValidate="0" />
    <ProxyItem Type="0" IP="115.223.245.186" Port="9000" UserName="" PassWord="" Domain="" IsValidate="0" />
    <ProxyItem Type="0" IP="202.107.238.51" Port="3128" UserName="" PassWord="" Domain="" IsValidate="0" />
    <ProxyItem Type="0" IP="115.223.247.129" Port="9000" UserName="" PassWord="" Domain="" IsValidate="0" />
    <ProxyItem Type="0" IP="118.249.116.110" Port="9000" UserName="" PassWord="" Domain="" IsValidate="0" />
    <ProxyItem Type="0" IP="218.95.81.194" Port="9000" UserName="" PassWord="" Domain="" IsValidate="0" />
    <ProxyItem Type="0" IP="175.153.82.232" Port="9000" UserName="" PassWord="" Domain="" IsValidate="0" />
    <ProxyItem Type="0" IP="112.64.29.42" Port="8090" UserName="" PassWord="" Domain="" IsValidate="0" />
    <ProxyItem Type="0" IP="115.223.218.6" Port="9000" UserName="" PassWord="" Domain="" IsValidate="0" />
  </Level2Proxys>
</Proxy>